[
  {
    "id": "8b5bf2fc-fd8e-4c6e-9287-fa05c0a3a127",
    "slug": "luxury-villa-ajmer",
    "title": "Luxury Villa",
    "description": "Spacious 3 BHK luxury villa with modern amenities, landscaped garden, and premium finishes. Ideal for families seeking comfort and elegance in Ajmer.",
    "price": 9500000,
    "location": "Ajmer",
    "address": "Vaishali Nagar, Ajmer",
    "area": 2200,
    "areaUnit": "sqft",
    "propertyType": "villa",
    "bedrooms": 3,
    "bathrooms": 3,
    "status": "sale",
    "amenities": [
      "Parking",
      "Garden",
      "Modular Kitchen",
      "Power Backup",
      "Security"
    ],
    "images": [
      "https://images.unsplash.com/photo-1613490493576-7fde63acd811?w=800&q=80",
      "https://images.unsplash.com/photo-1600596542815-ffad4c1539a9?w=800&q=80",
      "https://images.unsplash.com/photo-1600585154340-be6161a56a0c?w=800&q=80"
    ],
    "contactNumber": "+919414435920",
    "featured": true,
    "hidden": false,
    "createdAt": "2026-07-09T19:21:07.777Z",
    "updatedAt": "2026-07-09T19:21:07.777Z"
  },
  {
    "id": "1b49e263-7451-45c9-9673-0289ce179296",
    "slug": "commercial-office-vaishali-nagar",
    "title": "Commercial Office Space",
    "description": "Premium commercial office space in Vaishali Nagar with excellent connectivity, ample parking, and modern infrastructure. Perfect for businesses and startups.",
    "price": 18000000,
    "location": "Vaishali Nagar, Ajmer",
    "address": "Vaishali Nagar Main Road, Ajmer",
    "area": 4500,
    "areaUnit": "sqft",
    "propertyType": "commercial",
    "status": "sale",
    "amenities": [
      "Parking",
      "Lift",
      "Power Backup",
      "CCTV",
      "Fire Safety"
    ],
    "images": [
      "https://images.unsplash.com/photo-1497366216548-37526070297c?w=800&q=80",
      "https://images.unsplash.com/photo-1497366754035-f200968a6e72?w=800&q=80"
    ],
    "contactNumber": "+919414435920",
    "featured": true,
    "hidden": false,
    "createdAt": "2026-07-09T19:21:07.777Z",
    "updatedAt": "2026-07-09T19:21:07.777Z"
  },
  {
    "id": "f64b92cd-2535-4de7-9798-01a07b683e3a",
    "slug": "residential-plot-makarwali",
    "title": "Residential Plot",
    "description": "Well-located residential plot in Makarwali with clear title and all approvals. Ideal for building your dream home in a growing neighborhood.",
    "price": 3500000,
    "location": "Makarwali, Ajmer",
    "address": "Makarwali Road, Ajmer",
    "area": 1800,
    "areaUnit": "sqft",
    "propertyType": "plot",
    "status": "sale",
    "amenities": [
      "Clear Title",
      "Road Access",
      "Water Connection"
    ],
    "images": [
      "https://images.unsplash.com/photo-1500382017468-9049fed747ef?w=800&q=80",
      "https://images.unsplash.com/photo-1560518883-ce09059eeffa?w=800&q=80"
    ],
    "contactNumber": "+919414435920",
    "featured": true,
    "hidden": false,
    "createdAt": "2026-07-09T19:21:07.777Z",
    "updatedAt": "2026-07-09T19:21:07.777Z"
  },
  {
    "id": "34176999-8c17-4e72-9c76-d99e9be836a1",
    "slug": "3bhk-apartment-ajmer",
    "title": "3 BHK Modern Apartment",
    "description": "Beautiful 3 BHK apartment with balcony views, community amenities, and close proximity to schools and markets.",
    "price": 6500000,
    "location": "Ajmer City",
    "address": "Civil Lines, Ajmer",
    "area": 1650,
    "areaUnit": "sqft",
    "propertyType": "residential",
    "bedrooms": 3,
    "bathrooms": 2,
    "status": "sale",
    "amenities": [
      "Lift",
      "Parking",
      "Gym",
      "Club House",
      "24/7 Security"
    ],
    "images": [
      "https://images.unsplash.com/photo-1502672260266-1c1ef2d93688?w=800&q=80",
      "https://images.unsplash.com/photo-1522708323590-d24dbb6b0267?w=800&q=80"
    ],
    "contactNumber": "+919414435920",
    "featured": false,
    "hidden": false,
    "createdAt": "2026-07-09T19:21:07.777Z",
    "updatedAt": "2026-07-09T19:21:07.777Z"
  },
  {
    "id": "1e8a355d-b72e-493e-8333-f23fc51e0c04",
    "slug": "shop-vaishali-nagar",
    "title": "Prime Shop for Rent",
    "description": "High-footfall shop on main road in Vaishali Nagar. Ideal for retail, showroom, or office use.",
    "price": 25000,
    "location": "Vaishali Nagar, Ajmer",
    "address": "Main Market, Vaishali Nagar",
    "area": 600,
    "areaUnit": "sqft",
    "propertyType": "shop",
    "status": "rent",
    "amenities": [
      "Main Road Facing",
      "Parking Nearby"
    ],
    "images": [
      "https://images.unsplash.com/photo-1441986300917-64674bd600d8?w=800&q=80"
    ],
    "contactNumber": "+919414435920",
    "featured": false,
    "hidden": false,
    "createdAt": "2026-07-09T19:21:07.777Z",
    "updatedAt": "2026-07-09T19:21:07.777Z"
  }
]